setup.py
TracMyTickets.egg-info/PKG-INFO
TracMyTickets.egg-info/SOURCES.txt
TracMyTickets.egg-info/dependency_links.txt
TracMyTickets.egg-info/entry_points.txt
TracMyTickets.egg-info/top_level.txt
mytickets/__init__.py
mytickets/macro.py
