Metadata-Version: 1.0
Name: TracMyTickets
Version: 1.0
Summary: A simple macro to show your tickets.
Home-page: http://trac-hacks.org/wiki/MyTicketsPlugin
Author: Noah Kantrowitz
Author-email: coderanger@yahoo.com
License: BSD
Keywords: trac plugin macro tickets query
Platform: UNKNOWN
Classifier: Framework :: Trac
